rlp/__init__.py
rlp/atomic.py
rlp/codec.py
rlp/exceptions.py
rlp/lazy.py
rlp/utils.py
rlp/sedes/__init__.py
rlp/sedes/big_endian_int.py
rlp/sedes/binary.py
rlp/sedes/boolean.py
rlp/sedes/lists.py
rlp/sedes/raw.py
rlp/sedes/serializable.py
rlp/sedes/text.py
rlp-4.0.1.dist-info/LICENSE
rlp-4.0.1.dist-info/METADATA
rlp-4.0.1.dist-info/WHEEL
rlp-4.0.1.dist-info/top_level.txt
rlp-4.0.1.dist-info/RECORD
